jampack/__init__.py
jampack/jp.py
jampack/pack.py
jampack/settings.py
jampack/unpack.py
jampack/commands/__init__.py
jampack-0.9.4.dist-info/DESCRIPTION.rst
jampack-0.9.4.dist-info/entry_points.txt
jampack-0.9.4.dist-info/METADATA
jampack-0.9.4.dist-info/metadata.json
jampack-0.9.4.dist-info/RECORD
jampack-0.9.4.dist-info/top_level.txt
jampack-0.9.4.dist-info/WHEEL
