Metadata-Version: 2.0
Name: jampack
Version: 0.9.4
Summary: Simple file archives for everyone (tar.gz + tar.bz2 + zip)
Home-page: https://github.com/chrissimpkins/jampack
Author: Christopher Simpkins
Author-email: git.simpkins@gmail.com
License: MIT license
Keywords: tar,gz,gzip,zip,bzip,bzip2,bz2,archive,package,unpack,pack,jampack,jam,unjam
Platform: any
Classifier: Intended Audience :: End Users/Desktop
Classifier: Development Status :: 4 - Beta
Classifier: Natural Language :: English
Classifier: License :: OSI Approved :: MIT License
Classifier: Programming Language :: Python
Classifier: Programming Language :: Python :: 2
Classifier: Programming Language :: Python :: 3
Classifier: Operating System :: MacOS :: MacOS X
Classifier: Operating System :: POSIX
Classifier: Operating System :: Unix
Classifier: Operating System :: Microsoft :: Windows
Requires-Dist: Naked
Requires-Dist: colorama
